distutils-stubs/METADATA.toml
distutils-stubs/__init__.pyi
distutils-stubs/_modified.pyi
distutils-stubs/_msvccompiler.pyi
distutils-stubs/archive_util.pyi
distutils-stubs/ccompiler.pyi
distutils-stubs/cmd.pyi
distutils-stubs/dep_util.pyi
distutils-stubs/dist.pyi
distutils-stubs/errors.pyi
distutils-stubs/extension.pyi
distutils-stubs/filelist.pyi
distutils-stubs/py.typed
distutils-stubs/spawn.pyi
distutils-stubs/sysconfig.pyi
distutils-stubs/unixccompiler.pyi
distutils-stubs/util.pyi
distutils-stubs/command/__init__.pyi
distutils-stubs/command/bdist.pyi
distutils-stubs/command/bdist_rpm.pyi
distutils-stubs/command/build.pyi
distutils-stubs/command/build_clib.pyi
distutils-stubs/command/build_ext.pyi
distutils-stubs/command/build_py.pyi
distutils-stubs/command/install.pyi
distutils-stubs/command/install_data.pyi
distutils-stubs/command/install_lib.pyi
distutils-stubs/command/install_scripts.pyi
distutils-stubs/command/sdist.pyi
distutils-stubs/compat/__init__.pyi
distutils-stubs/compilers/C/base.pyi
distutils-stubs/compilers/C/errors.pyi
distutils-stubs/compilers/C/msvc.pyi
distutils-stubs/compilers/C/unix.pyi
setuptools-stubs/METADATA.toml
setuptools-stubs/__init__.pyi
setuptools-stubs/archive_util.pyi
setuptools-stubs/build_meta.pyi
setuptools-stubs/depends.pyi
setuptools-stubs/discovery.pyi
setuptools-stubs/dist.pyi
setuptools-stubs/errors.pyi
setuptools-stubs/extension.pyi
setuptools-stubs/glob.pyi
setuptools-stubs/installer.pyi
setuptools-stubs/launch.pyi
setuptools-stubs/logging.pyi
setuptools-stubs/modified.pyi
setuptools-stubs/monkey.pyi
setuptools-stubs/msvc.pyi
setuptools-stubs/namespaces.pyi
setuptools-stubs/py.typed
setuptools-stubs/unicode_utils.pyi
setuptools-stubs/version.pyi
setuptools-stubs/warnings.pyi
setuptools-stubs/wheel.pyi
setuptools-stubs/windows_support.pyi
setuptools-stubs/_distutils/__init__.pyi
setuptools-stubs/_distutils/_modified.pyi
setuptools-stubs/_distutils/_msvccompiler.pyi
setuptools-stubs/_distutils/archive_util.pyi
types_setuptools-80.9.0.20250801.dist-info/licenses/LICENSE
types_setuptools-80.9.0.20250801.dist-info/METADATA
types_setuptools-80.9.0.20250801.dist-info/WHEEL
types_setuptools-80.9.0.20250801.dist-info/top_level.txt
types_setuptools-80.9.0.20250801.dist-info/RECORD
